django_snowflake/__init__.py
django_snowflake/aggregates.py
django_snowflake/base.py
django_snowflake/client.py
django_snowflake/compiler.py
django_snowflake/creation.py
django_snowflake/expressions.py
django_snowflake/features.py
django_snowflake/functions.py
django_snowflake/introspection.py
django_snowflake/lookups.py
django_snowflake/operations.py
django_snowflake/schema.py
django_snowflake/utils.py
django_snowflake-6.0.dist-info/licenses/LICENSE
django_snowflake-6.0.dist-info/METADATA
django_snowflake-6.0.dist-info/WHEEL
django_snowflake-6.0.dist-info/top_level.txt
django_snowflake-6.0.dist-info/RECORD
