Metadata-Version: 2.4
Name: django-snowflake
Version: 6.0
Summary: Django backend for Snowflake
Home-page: https://github.com/Snowflake-Labs/django-snowflake
Maintainer: Tim Graham
Maintainer-email: timograham@gmail.com
License: MIT License
Project-URL: Source, https://github.com/Snowflake-Labs/django-snowflake
Project-URL: Tracker, https://github.com/Snowflake-Labs/django-snowflake/issues
Classifier: Development Status :: 5 - Production/Stable
Classifier: Framework :: Django
Classifier: Framework :: Django :: 6.0
Classifier: License :: OSI Approved :: MIT License
Classifier: Operating System :: OS Independent
Classifier: Programming Language :: Python
Classifier: Programming Language :: Python :: 3
Classifier: Programming Language :: Python :: 3.12
Classifier: Programming Language :: Python :: 3.13
Classifier: Programming Language :: Python :: 3.14
Requires-Python: >=3.12
License-File: LICENSE
Requires-Dist: django<6.1,>=6.0
Requires-Dist: snowflake-connector-python>=3.6.0
Dynamic: license-file
